[
  {
    "title": "High \u0026 Dry",
    "description": "High and Dry uses Viva New Vegas as a base and builds off of its stability with more added mods that bring you better gameplay, visuals, animations, and user interface experiences all while making the game feel updated and new with different overhauls and content.",
    "author": "Jayer117",
    "maintainers": [
      "github/Jayer117-ball"
    ],
    "game": "falloutnewvegas",
    "official": false,
    "tags": [
      "Stability",
      "Consistent",
      "Visuals",
      "Gameplay",
      "Lore-friendly"
    ],
    "nsfw": false,
    "utility_list": false,
    "image_contains_title": true,
    "DisplayVersionOnlyInInstallerView": false,
    "force_down": false,
    "links": {
      "image": "https://raw.githubusercontent.com/Jayer117-ball/HighandDry/main/cropped-HighandDryWJ.png",
      "readme": "https://github.com/Jayer117-ball/HighandDry/blob/main/README.md",
      "download": "https://authored-files.wabbajack.org/High and Dry.wabbajack_fb67b3f5-57b5-4909-b01c-ecea4d48fdeb",
      "machineURL": "highanddry",
      "discordURL": "https://discord.gg/zV5zACunk3",
      "websiteURL": "https://github.com/Jayer117-ball/HighandDry/blob/main/README.md"
    },
    "download_metadata": {
      "Hash": "Pl86sJKp63o=",
      "Size": 296869222,
      "NumberOfArchives": 1109,
      "SizeOfArchives": 35029758383,
      "NumberOfInstalledFiles": 130142,
      "SizeOfInstalledFiles": 67793096163,
      "TotalSize": 102822854546
    },
    "version": "4.9.6",
    "dateCreated": "1970-01-01T00:00:00Z",
    "dateUpdated": "2026-02-06T12:27:36.6801442Z",
    "repositoryName": ""
  }
]